MANIFEST.in
README
README.rst
setup.py
oauthnesia/__init__.py
oauthnesia.egg-info/PKG-INFO
oauthnesia.egg-info/SOURCES.txt
oauthnesia.egg-info/dependency_links.txt
oauthnesia.egg-info/not-zip-safe
oauthnesia.egg-info/requires.txt
oauthnesia.egg-info/top_level.txt