Metadata-Version: 1.0
Name: oauthnesia
Version: 1.0.5
Summary: Client for Urbanesia's OAUTH v1.0a API
Home-page: http://github.com/Urbanesia/oauthnesia-py
Author: Batista Harahap
Author-email: tista@urbanesia.com
License: MIT
Keywords: urbanesia oauth poi web service api
Platform: UNKNOWN
